{
    "key": "group_5d98d8ed399af",
    "title": "Block : Gage de qualité",
    "fields": [
        {
            "key": "field_5d98d8f67ac7a",
            "label": "Titre de la section",
            "name": "title_quality_presta",
            "type": "text",
            "instructions": "",
            "required": 0,
            "conditional_logic": 0,
            "wrapper": {
                "width": "",
                "class": "",
                "id": ""
            },
            "default_value": "",
            "placeholder": "",
            "prepend": "",
            "append": "",
            "maxlength": ""
        },
        {
            "key": "field_5d98d8ff7ac7b",
            "label": "Répéteur",
            "name": "quality_repeater",
            "type": "repeater",
            "instructions": "",
            "required": 0,
            "conditional_logic": 0,
            "wrapper": {
                "width": "",
                "class": "",
                "id": ""
            },
            "collapsed": "",
            "min": 0,
            "max": 0,
            "layout": "block",
            "button_label": "Ajouter un Gage de qualité",
            "sub_fields": [
                {
                    "key": "field_5d98d94c7ac7d",
                    "label": "Titre du gage de qualité",
                    "name": "title_quality",
                    "type": "text",
                    "instructions": "",
                    "required": 0,
                    "conditional_logic": 0,
                    "wrapper": {
                        "width": "",
                        "class": "",
                        "id": ""
                    },
                    "default_value": "",
                    "placeholder": "",
                    "prepend": "",
                    "append": "",
                    "maxlength": ""
                },
                {
                    "key": "field_5d98d9a67ac7e",
                    "label": "Petite description (optionnel)",
                    "name": "quality_description",
                    "type": "text",
                    "instructions": "",
                    "required": 0,
                    "conditional_logic": 0,
                    "wrapper": {
                        "width": "",
                        "class": "",
                        "id": ""
                    },
                    "default_value": "",
                    "placeholder": "",
                    "prepend": "",
                    "append": "",
                    "maxlength": ""
                },
                {
                    "key": "field_5d98d9bd7ac7f",
                    "label": "Image\/pictogramme\/logo",
                    "name": "quality_picture",
                    "type": "image",
                    "instructions": "",
                    "required": 0,
                    "conditional_logic": 0,
                    "wrapper": {
                        "width": "",
                        "class": "",
                        "id": ""
                    },
                    "return_format": "id",
                    "preview_size": "medium",
                    "library": "all",
                    "min_width": "",
                    "min_height": "",
                    "min_size": "",
                    "max_width": "",
                    "max_height": "",
                    "max_size": "",
                    "mime_types": ""
                },
                {
                    "key": "field_5d98d9ef7ac80",
                    "label": "Block de text de gauche",
                    "name": "quality_block_left",
                    "type": "textarea",
                    "instructions": "",
                    "required": 0,
                    "conditional_logic": 0,
                    "wrapper": {
                        "width": "",
                        "class": "",
                        "id": ""
                    },
                    "default_value": "",
                    "placeholder": "",
                    "maxlength": "",
                    "rows": "",
                    "new_lines": ""
                },
                {
                    "key": "field_5d98da077ac81",
                    "label": "Block de text de droite",
                    "name": "quality_block_right",
                    "type": "textarea",
                    "instructions": "",
                    "required": 0,
                    "conditional_logic": 0,
                    "wrapper": {
                        "width": "",
                        "class": "",
                        "id": ""
                    },
                    "default_value": "",
                    "placeholder": "",
                    "maxlength": "",
                    "rows": "",
                    "new_lines": ""
                },
                {
                    "key": "field_5d98da207ac82",
                    "label": "Choix du style",
                    "name": "quality_flexible_content",
                    "type": "flexible_content",
                    "instructions": "",
                    "required": 0,
                    "conditional_logic": 0,
                    "wrapper": {
                        "width": "",
                        "class": "",
                        "id": ""
                    },
                    "layouts": {
                        "layout_5d98da475edc8": {
                            "key": "layout_5d98da475edc8",
                            "name": "column_style",
                            "label": "Style Colonne",
                            "display": "block",
                            "sub_fields": [
                                {
                                    "key": "field_5d98dab47ac83",
                                    "label": "Ajouter des colonnes",
                                    "name": "column_repeater",
                                    "type": "repeater",
                                    "instructions": "",
                                    "required": 0,
                                    "conditional_logic": 0,
                                    "wrapper": {
                                        "width": "",
                                        "class": "",
                                        "id": ""
                                    },
                                    "collapsed": "",
                                    "min": 0,
                                    "max": 0,
                                    "layout": "table",
                                    "button_label": "Ajouter une colonne",
                                    "sub_fields": [
                                        {
                                            "key": "field_5d98db117ac85",
                                            "label": "Titre de la colonne",
                                            "name": "column_title",
                                            "type": "text",
                                            "instructions": "",
                                            "required": 0,
                                            "conditional_logic": 0,
                                            "wrapper": {
                                                "width": "",
                                                "class": "",
                                                "id": ""
                                            },
                                            "default_value": "",
                                            "placeholder": "",
                                            "prepend": "",
                                            "append": "",
                                            "maxlength": ""
                                        },
                                        {
                                            "key": "field_5d98db257ac86",
                                            "label": "Texte de la colonne",
                                            "name": "column_text",
                                            "type": "text",
                                            "instructions": "",
                                            "required": 0,
                                            "conditional_logic": 0,
                                            "wrapper": {
                                                "width": "",
                                                "class": "",
                                                "id": ""
                                            },
                                            "default_value": "",
                                            "placeholder": "",
                                            "prepend": "",
                                            "append": "",
                                            "maxlength": ""
                                        }
                                    ]
                                }
                            ],
                            "min": "",
                            "max": ""
                        }
                    },
                    "button_label": "Ajouter un élément",
                    "min": "",
                    "max": ""
                }
            ]
        }
    ],
    "location": [
        [
            {
                "param": "block",
                "operator": "==",
                "value": "acf\/quality"
            }
        ]
    ],
    "menu_order": 0,
    "position": "normal",
    "style": "default",
    "label_placement": "top",
    "instruction_placement": "label",
    "hide_on_screen": "",
    "active": 1,
    "description": "",
    "modified": 1572863922
}